taskcontrol/__init__.py
taskcontrol/bases.py
taskcontrol/pubsub.py
taskcontrol/workflow.py
taskcontrol-1.1.2.dist-info/LICENSE
taskcontrol-1.1.2.dist-info/METADATA
taskcontrol-1.1.2.dist-info/WHEEL
taskcontrol-1.1.2.dist-info/top_level.txt
taskcontrol-1.1.2.dist-info/RECORD
