Metadata-Version: 2.1
Name: taskcontrol
Version: 1.1.2
Summary: Create named isolated/shared workflow task controls and run the tasks with respective before and after middlewares in ordered manner
Home-page: https://github.com/ganeshkbhat/taskcontrol
Author: Ganesh B
Author-email: ganeshsurfs@gmail.com
License: UNKNOWN
Platform: UNKNOWN
Classifier: Programming Language :: Python :: 3
Classifier: License :: OSI Approved :: MIT License
Classifier: Operating System :: OS Independent
